{
    "IsActive": true,
    "IsOmniScriptEmbeddable": false,
    "Name": "SetSelectedProductsError",
    "OmniProcessId": {
        "Name": "CreateServiceQuote",
        "VlocityDataPackType": "VlocityMatchingKeyObject",
        "VlocityMatchingRecordSourceKey": "OmniProcess/PlusNet/CreateServiceQuote/German",
        "VlocityRecordSObjectType": "OmniProcess"
    },
    "PropertySetConfig": {
        "HTMLTemplateId": "",
        "controlWidth": 12,
        "elementErrorMap": {
            "BandwidthSelection": "Please Select a Product"
        },
        "label": "",
        "message": {
        },
        "pubsub": false,
        "show": {
            "group": {
                "operator": "AND",
                "rules": [
                    {
                        "condition": "=",
                        "data": "false",
                        "field": "OfferProdSelected"
                    }
                ]
            }
        },
        "showPersistentComponent": [
            true,
            false
        ],
        "ssm": false,
        "validationRequired": "Step",
        "wpm": false
    },
    "Type": "Set Errors",
    "VlocityDataPackType": "SObject",
    "VlocityRecordSObjectType": "OmniProcessElement",
    "VlocityRecordSourceKey": "OmniProcessElement/OmniProcess/PlusNet/CreateServiceQuote/German/SetSelectedProductsError"
}