{
    "IsActive": true,
    "IsOmniScriptEmbeddable": false,
    "Name": "MaintainCLIs",
    "OmniProcessId": {
        "Name": "Change Contract Handler",
        "VlocityDataPackType": "VlocityMatchingKeyObject",
        "VlocityMatchingRecordSourceKey": "OmniProcess/PlusNet/ChangeContractHandler/Procedure",
        "VlocityRecordSObjectType": "OmniProcess"
    },
    "PropertySetConfig": {
        "disOnTplt": false,
        "executionConditionalFormula": "%OrderType% != 'Termination'",
        "isIfElseBlock": false,
        "label": "ConditionalBlock1",
        "show": null
    },
    "Type": "Conditional Block",
    "VlocityDataPackType": "SObject",
    "VlocityRecordSObjectType": "OmniProcessElement",
    "VlocityRecordSourceKey": "OmniProcessElement/OmniProcess/PlusNet/ChangeContractHandler/Procedure/MaintainCLIs"
}