{
    "IsActive": true,
    "IsOmniScriptEmbeddable": false,
    "Name": "GetPremiseOwnerAccountDetails",
    "OmniProcessId": {
        "Name": "CreateConnectionQuote",
        "VlocityDataPackType": "VlocityMatchingKeyObject",
        "VlocityMatchingRecordSourceKey": "OmniProcess/PlusNet/CreateConnectionQuote/German",
        "VlocityRecordSObjectType": "OmniProcess"
    },
    "PropertySetConfig": {
        "HTMLTemplateId": "",
        "bundle": "GetPremiseOwnerAccountDetails",
        "businessCategory": "",
        "businessEvent": "",
        "controlWidth": 12,
        "dataRaptor Input Parameters": [
            {
                "element": "premiseOwnerAccountId",
                "inputParam": "PremiseOwnerAccountId"
            }
        ],
        "enableActionMessage": false,
        "enableDefaultAbort": false,
        "errorMessage": {
            "custom": [
            ],
            "default": null
        },
        "failureAbortLabel": "Abort",
        "failureAbortMessage": "Are you sure?",
        "failureGoBackLabel": "Go Back",
        "failureNextLabel": "Continue",
        "ignoreCache": false,
        "inProgressMessage": "In Progress",
        "label": "GetPremiseOwnerAccountDetails",
        "message": {
        },
        "postMessage": "Done",
        "pubsub": false,
        "redirectNextLabel": "Next",
        "redirectNextWidth": 3,
        "redirectPageName": "",
        "redirectPreviousLabel": "Previous",
        "redirectPreviousWidth": 3,
        "redirectTemplateUrl": "vlcAcknowledge.html",
        "remoteTimeout": 30000,
        "responseJSONNode": "",
        "responseJSONPath": "",
        "show": {
            "group": {
                "operator": "AND",
                "rules": [
                    {
                        "condition": "=",
                        "data": "Case",
                        "field": "Context"
                    },
                    {
                        "condition": "=",
                        "data": "Owner Identified",
                        "field": "status"
                    },
                    {
                        "condition": "<>",
                        "data": null,
                        "field": "premiseOwnerAccountId"
                    }
                ]
            }
        },
        "showPersistentComponent": [
            true,
            false
        ],
        "ssm": false,
        "validationRequired": "Step",
        "wpm": false
    },
    "Type": "DataRaptor Extract Action",
    "VlocityDataPackType": "SObject",
    "VlocityRecordSObjectType": "OmniProcessElement",
    "VlocityRecordSourceKey": "OmniProcessElement/OmniProcess/PlusNet/CreateConnectionQuote/German/GetPremiseOwnerAccountDetails"
}