{
    "IsActive": true,
    "IsOmniScriptEmbeddable": false,
    "Name": "NavigateToFiberOS",
    "OmniProcessId": {
        "Name": "CreateQuote",
        "VlocityDataPackType": "VlocityMatchingKeyObject",
        "VlocityMatchingRecordSourceKey": "OmniProcess/PlusNet/CreateQuote/German",
        "VlocityRecordSObjectType": "OmniProcess"
    },
    "PropertySetConfig": {
        "HTMLTemplateId": "",
        "businessCategory": "",
        "businessEvent": "",
        "controlWidth": 12,
        "iconName": "",
        "iconPosition": "left",
        "iconVariant": "",
        "label": "NavigateAction1",
        "loginAction": "login",
        "message": {
        },
        "objectAction": "home",
        "pubsub": false,
        "recordAction": "view",
        "replace": true,
        "show": {
            "group": {
                "operator": "OR",
                "rules": [
                    {
                        "condition": "=",
                        "data": "Office",
                        "field": "productType"
                    },
                    {
                        "condition": "=",
                        "data": "Business",
                        "field": "productType"
                    }
                ]
            }
        },
        "ssm": false,
        "targetFilter": "Recent",
        "targetId": "%ContextId%",
        "targetLWC": "c:plusNetCreateServiceQuoteGerman",
        "targetLWCLayout": "lightning",
        "targetLWCParams": "c__ContextId=%OpportunityDetails:Id%&c__accountId=%OpportunityDetails:AccountId%&c__contactId=%OpportunityDetails:ContactId%&c__premiseId=%selectedAddress:premiseId%&c__marketingPhase=%marketingPhase%&c__productType=%productType%&c__productFamily=%productFamily%&c__maxBandwidth=\"%maxbandwidth%\"&c__externalId=%externalId%",
        "targetType": "Vlocity OmniScript",
        "validationRequired": "Submit",
        "variant": "brand",
        "wpm": false
    },
    "Type": "Navigate Action",
    "VlocityDataPackType": "SObject",
    "VlocityRecordSObjectType": "OmniProcessElement",
    "VlocityRecordSourceKey": "OmniProcessElement/OmniProcess/PlusNet/CreateQuote/German/NavigateToFiberOS"
}