{
    "IsActive": true,
    "IsOmniScriptEmbeddable": false,
    "Name": "IsContractCreated",
    "OmniProcessId": {
        "Name": "CreateContractActivationQuote",
        "VlocityDataPackType": "VlocityMatchingKeyObject",
        "VlocityMatchingRecordSourceKey": "OmniProcess/PlusNet/CreateContractActivationQuote/Procedure",
        "VlocityRecordSObjectType": "OmniProcess"
    },
    "PropertySetConfig": {
        "disOnTplt": false,
        "executionConditionalFormula": "ISNOTBLANK(%CreateContract:ContractId%)",
        "isIfElseBlock": false,
        "label": "ConditionalBlock1",
        "show": null
    },
    "Type": "Conditional Block",
    "VlocityDataPackType": "SObject",
    "VlocityRecordSObjectType": "OmniProcessElement",
    "VlocityRecordSourceKey": "OmniProcessElement/OmniProcess/PlusNet/CreateContractActivationQuote/Procedure/IsContractCreated"
}