{
    "IsActive": true,
    "IsOmniScriptEmbeddable": false,
    "Name": "TextBlock3",
    "OmniProcessId": {
        "Name": "QuoteOrderCancellation",
        "VlocityDataPackType": "VlocityMatchingKeyObject",
        "VlocityMatchingRecordSourceKey": "OmniProcess/PlusNet/QuoteAndOrderCancellation/Multi-Language",
        "VlocityRecordSObjectType": "OmniProcess"
    },
    "ParentElementId": {
        "Name": "CancellarionError",
        "OmniProcessId": {
            "Name": "QuoteOrderCancellation",
            "VlocityDataPackType": "VlocityMatchingKeyObject",
            "VlocityMatchingRecordSourceKey": "OmniProcess/PlusNet/QuoteAndOrderCancellation/Multi-Language",
            "VlocityRecordSObjectType": "OmniProcess"
        },
        "VlocityDataPackType": "VlocityMatchingKeyObject",
        "VlocityMatchingRecordSourceKey": "OmniProcessElement/OmniProcess/PlusNet/QuoteAndOrderCancellation/Multi-Language/CancellarionError",
        "VlocityRecordSObjectType": "OmniProcessElement"
    },
    "ParentElementName": "CancellarionError",
    "ParentElementType": "Step",
    "PropertySetConfig": {
        "HTMLTemplateId": "",
        "controlWidth": 12,
        "dataJSON": false,
        "label": "PlusNet_Quote_cannot_be_cancelled",
        "sanitize": false,
        "show": {
            "group": {
                "operator": "AND",
                "rules": [
                    {
                        "condition": "=",
                        "data": "Quote",
                        "field": "CancellationContext"
                    }
                ]
            }
        },
        "text": "",
        "textKey": "PlusNet_Quote_cannot_be_cancelled"
    },
    "Type": "Text Block",
    "VlocityDataPackType": "SObject",
    "VlocityRecordSObjectType": "OmniProcessElement",
    "VlocityRecordSourceKey": "OmniProcessElement/OmniProcess/PlusNet/QuoteAndOrderCancellation/Multi-Language/TextBlock3"
}