[
    {
        "%vlocity_namespace%__CompiledAttributeOverrideId__c": {
            "VlocityDataPackType": "VlocityMatchingKeyObject",
            "VlocityMatchingRecordSourceKey": "%vlocity_namespace%__CompiledAttributeOverride__c/Generated-1922937255",
            "VlocityRecordSObjectType": "%vlocity_namespace%__CompiledAttributeOverride__c"
        },
        "%vlocity_namespace%__IsExclude__c": false,
        "%vlocity_namespace%__OverriddenAttributeAssignmentCategoryId__c": {
            "%vlocity_namespace%__Code__c": "ATTCAT-B2B-GNR-ATT",
            "VlocityDataPackType": "VlocityLookupMatchingKeyObject",
            "VlocityLookupRecordSourceKey": "%vlocity_namespace%__AttributeCategory__c/ATTCAT-B2B-GNR-ATT",
            "VlocityRecordSObjectType": "%vlocity_namespace%__AttributeCategory__c"
        },
        "%vlocity_namespace%__OverriddenAttributeAssignmentId__c": {
            "%vlocity_namespace%__AttributeId__r.%vlocity_namespace%__Code__c": "ATT-OFF-CODE",
            "%vlocity_namespace%__IsOverride__c": false,
            "%vlocity_namespace%__ObjectId__c": {
                "%vlocity_namespace%__GlobalKey__c": "b34437aa-628c-b1d2-59f6-30be8219b8c2",
                "VlocityDataPackType": "VlocityLookupMatchingKeyObject",
                "VlocityLookupRecordSourceKey": "Product2/b34437aa-628c-b1d2-59f6-30be8219b8c2",
                "VlocityRecordSObjectType": "Product2"
            },
            "%vlocity_namespace%__OverrideContext__c": null,
            "VlocityDataPackType": "VlocityLookupMatchingKeyObject",
            "VlocityLookupRecordSourceKey": "%vlocity_namespace%__AttributeAssignment__c/d7363cde-f42e-bf6e-2d68-95c20d7d4ca8",
            "VlocityRecordSObjectType": "%vlocity_namespace%__AttributeAssignment__c"
        },
        "%vlocity_namespace%__OverrideType__c": "Attribute",
        "%vlocity_namespace%__OverridingAttributeAssignmentCategoryId__c": {
            "%vlocity_namespace%__Code__c": "ATTCAT-B2B-GNR-ATT",
            "VlocityDataPackType": "VlocityLookupMatchingKeyObject",
            "VlocityLookupRecordSourceKey": "%vlocity_namespace%__AttributeCategory__c/ATTCAT-B2B-GNR-ATT",
            "VlocityRecordSObjectType": "%vlocity_namespace%__AttributeCategory__c"
        },
        "%vlocity_namespace%__OverridingAttributeAssignmentId__c": {
            "%vlocity_namespace%__AttributeId__r.%vlocity_namespace%__Code__c": "ATT-OFF-CODE",
            "%vlocity_namespace%__IsOverride__c": true,
            "%vlocity_namespace%__ObjectId__c": {
                "%vlocity_namespace%__GlobalKey__c": "b34437aa-628c-b1d2-59f6-30be8219b8c2",
                "VlocityDataPackType": "VlocityLookupMatchingKeyObject",
                "VlocityLookupRecordSourceKey": "Product2/b34437aa-628c-b1d2-59f6-30be8219b8c2",
                "VlocityRecordSObjectType": "Product2"
            },
            "%vlocity_namespace%__OverrideContext__c": "992757347",
            "VlocityDataPackType": "VlocityLookupMatchingKeyObject",
            "VlocityLookupRecordSourceKey": "%vlocity_namespace%__AttributeAssignment__c/1e99d154-cc14-9681-bba8-35fbe724183e",
            "VlocityRecordSObjectType": "%vlocity_namespace%__AttributeAssignment__c"
        },
        "%vlocity_namespace%__ProductGroupKey__c": "c2ad529d-a871-1bf5-feab-bcea157da521",
        "%vlocity_namespace%__ProductHierarchyGlobalKeyPath__c": "1915164a-99ea-a039-0705-2b296dfc277d<b34437aa-628c-b1d2-59f6-30be8219b8c2",
        "%vlocity_namespace%__ProductHierarchyGroupKeyPath__c": "c2ad529d-a871-1bf5-feab-bcea157da521<64ea5f79-f973-0eb3-5731-2f8aab975aa0",
        "%vlocity_namespace%__ProductHierarchyPath__c": "01t9M000008wrfFQAQ<01t9M000008eGW5QAM",
        "%vlocity_namespace%__ProductId__c": {
            "%vlocity_namespace%__GlobalKey__c": "1915164a-99ea-a039-0705-2b296dfc277d",
            "VlocityDataPackType": "VlocityMatchingKeyObject",
            "VlocityMatchingRecordSourceKey": "Product2/1915164a-99ea-a039-0705-2b296dfc277d",
            "VlocityRecordSObjectType": "Product2"
        },
        "Name": "OverrideDefinition",
        "VlocityDataPackType": "SObject",
        "VlocityRecordSObjectType": "%vlocity_namespace%__OverrideDefinition__c"
    },
    {
        "%vlocity_namespace%__CompiledAttributeOverrideId__c": {
            "VlocityDataPackType": "VlocityMatchingKeyObject",
            "VlocityMatchingRecordSourceKey": "%vlocity_namespace%__CompiledAttributeOverride__c/Generated-625990356",
            "VlocityRecordSObjectType": "%vlocity_namespace%__CompiledAttributeOverride__c"
        },
        "%vlocity_namespace%__IsExclude__c": false,
        "%vlocity_namespace%__OverriddenAttributeAssignmentCategoryId__c": {
            "%vlocity_namespace%__Code__c": "ATTCAT-B2B-GNR-ATT",
            "VlocityDataPackType": "VlocityLookupMatchingKeyObject",
            "VlocityLookupRecordSourceKey": "%vlocity_namespace%__AttributeCategory__c/ATTCAT-B2B-GNR-ATT",
            "VlocityRecordSObjectType": "%vlocity_namespace%__AttributeCategory__c"
        },
        "%vlocity_namespace%__OverriddenAttributeAssignmentId__c": {
            "%vlocity_namespace%__AttributeId__r.%vlocity_namespace%__Code__c": "ATT-OFF-CODE",
            "%vlocity_namespace%__IsOverride__c": false,
            "%vlocity_namespace%__ObjectId__c": {
                "%vlocity_namespace%__GlobalKey__c": "8ccbf96a-e729-224a-9085-24bccb8b94b5",
                "VlocityDataPackType": "VlocityLookupMatchingKeyObject",
                "VlocityLookupRecordSourceKey": "Product2/8ccbf96a-e729-224a-9085-24bccb8b94b5",
                "VlocityRecordSObjectType": "Product2"
            },
            "%vlocity_namespace%__OverrideContext__c": null,
            "VlocityDataPackType": "VlocityLookupMatchingKeyObject",
            "VlocityLookupRecordSourceKey": "%vlocity_namespace%__AttributeAssignment__c/9ff65f40-f0ab-a5e5-3436-2f2089d28b09",
            "VlocityRecordSObjectType": "%vlocity_namespace%__AttributeAssignment__c"
        },
        "%vlocity_namespace%__OverrideType__c": "Attribute",
        "%vlocity_namespace%__OverridingAttributeAssignmentCategoryId__c": {
            "%vlocity_namespace%__Code__c": "ATTCAT-B2B-GNR-ATT",
            "VlocityDataPackType": "VlocityLookupMatchingKeyObject",
            "VlocityLookupRecordSourceKey": "%vlocity_namespace%__AttributeCategory__c/ATTCAT-B2B-GNR-ATT",
            "VlocityRecordSObjectType": "%vlocity_namespace%__AttributeCategory__c"
        },
        "%vlocity_namespace%__OverridingAttributeAssignmentId__c": {
            "%vlocity_namespace%__AttributeId__r.%vlocity_namespace%__Code__c": "ATT-OFF-CODE",
            "%vlocity_namespace%__IsOverride__c": true,
            "%vlocity_namespace%__ObjectId__c": {
                "%vlocity_namespace%__GlobalKey__c": "8ccbf96a-e729-224a-9085-24bccb8b94b5",
                "VlocityDataPackType": "VlocityLookupMatchingKeyObject",
                "VlocityLookupRecordSourceKey": "Product2/8ccbf96a-e729-224a-9085-24bccb8b94b5",
                "VlocityRecordSObjectType": "Product2"
            },
            "%vlocity_namespace%__OverrideContext__c": "2210170403",
            "VlocityDataPackType": "VlocityLookupMatchingKeyObject",
            "VlocityLookupRecordSourceKey": "%vlocity_namespace%__AttributeAssignment__c/bfd2f78d-b484-3fe5-bfb6-a1acbd0a556b",
            "VlocityRecordSObjectType": "%vlocity_namespace%__AttributeAssignment__c"
        },
        "%vlocity_namespace%__ProductGroupKey__c": "c2ad529d-a871-1bf5-feab-bcea157da521",
        "%vlocity_namespace%__ProductHierarchyGlobalKeyPath__c": "1915164a-99ea-a039-0705-2b296dfc277d<8ccbf96a-e729-224a-9085-24bccb8b94b5",
        "%vlocity_namespace%__ProductHierarchyGroupKeyPath__c": "c2ad529d-a871-1bf5-feab-bcea157da521<0663d6a9-d7d2-8696-680e-485a931bf59a",
        "%vlocity_namespace%__ProductHierarchyPath__c": "01t9M000008wrfFQAQ<01tMU000000lEfHYAU",
        "%vlocity_namespace%__ProductId__c": {
            "%vlocity_namespace%__GlobalKey__c": "1915164a-99ea-a039-0705-2b296dfc277d",
            "VlocityDataPackType": "VlocityMatchingKeyObject",
            "VlocityMatchingRecordSourceKey": "Product2/1915164a-99ea-a039-0705-2b296dfc277d",
            "VlocityRecordSObjectType": "Product2"
        },
        "Name": "OverrideDefinition",
        "VlocityDataPackType": "SObject",
        "VlocityRecordSObjectType": "%vlocity_namespace%__OverrideDefinition__c"
    },
    {
        "%vlocity_namespace%__CompiledAttributeOverrideId__c": {
            "VlocityDataPackType": "VlocityMatchingKeyObject",
            "VlocityMatchingRecordSourceKey": "%vlocity_namespace%__CompiledAttributeOverride__c/Generated-625990356",
            "VlocityRecordSObjectType": "%vlocity_namespace%__CompiledAttributeOverride__c"
        },
        "%vlocity_namespace%__IsExclude__c": false,
        "%vlocity_namespace%__OverriddenAttributeAssignmentCategoryId__c": {
            "%vlocity_namespace%__Code__c": "ATTCAT-B2B-HRD-DTL",
            "VlocityDataPackType": "VlocityLookupMatchingKeyObject",
            "VlocityLookupRecordSourceKey": "%vlocity_namespace%__AttributeCategory__c/ATTCAT-B2B-HRD-DTL",
            "VlocityRecordSObjectType": "%vlocity_namespace%__AttributeCategory__c"
        },
        "%vlocity_namespace%__OverriddenAttributeAssignmentId__c": {
            "%vlocity_namespace%__AttributeId__r.%vlocity_namespace%__Code__c": "ATT-INT-TYP",
            "%vlocity_namespace%__IsOverride__c": false,
            "%vlocity_namespace%__ObjectId__c": {
                "%vlocity_namespace%__GlobalKey__c": "8ccbf96a-e729-224a-9085-24bccb8b94b5",
                "VlocityDataPackType": "VlocityLookupMatchingKeyObject",
                "VlocityLookupRecordSourceKey": "Product2/8ccbf96a-e729-224a-9085-24bccb8b94b5",
                "VlocityRecordSObjectType": "Product2"
            },
            "%vlocity_namespace%__OverrideContext__c": null,
            "VlocityDataPackType": "VlocityLookupMatchingKeyObject",
            "VlocityLookupRecordSourceKey": "%vlocity_namespace%__AttributeAssignment__c/73ca6a0a-45e2-58fa-986d-f2e44bd92ba2",
            "VlocityRecordSObjectType": "%vlocity_namespace%__AttributeAssignment__c"
        },
        "%vlocity_namespace%__OverrideType__c": "Attribute",
        "%vlocity_namespace%__OverridingAttributeAssignmentCategoryId__c": {
            "%vlocity_namespace%__Code__c": "ATTCAT-B2B-HRD-DTL",
            "VlocityDataPackType": "VlocityLookupMatchingKeyObject",
            "VlocityLookupRecordSourceKey": "%vlocity_namespace%__AttributeCategory__c/ATTCAT-B2B-HRD-DTL",
            "VlocityRecordSObjectType": "%vlocity_namespace%__AttributeCategory__c"
        },
        "%vlocity_namespace%__OverridingAttributeAssignmentId__c": {
            "%vlocity_namespace%__AttributeId__r.%vlocity_namespace%__Code__c": "ATT-INT-TYP",
            "%vlocity_namespace%__IsOverride__c": true,
            "%vlocity_namespace%__ObjectId__c": {
                "%vlocity_namespace%__GlobalKey__c": "8ccbf96a-e729-224a-9085-24bccb8b94b5",
                "VlocityDataPackType": "VlocityLookupMatchingKeyObject",
                "VlocityLookupRecordSourceKey": "Product2/8ccbf96a-e729-224a-9085-24bccb8b94b5",
                "VlocityRecordSObjectType": "Product2"
            },
            "%vlocity_namespace%__OverrideContext__c": "2210170403",
            "VlocityDataPackType": "VlocityLookupMatchingKeyObject",
            "VlocityLookupRecordSourceKey": "%vlocity_namespace%__AttributeAssignment__c/5064d513-b482-5c57-e2ad-ea8962c8c89d",
            "VlocityRecordSObjectType": "%vlocity_namespace%__AttributeAssignment__c"
        },
        "%vlocity_namespace%__ProductGroupKey__c": "c2ad529d-a871-1bf5-feab-bcea157da521",
        "%vlocity_namespace%__ProductHierarchyGlobalKeyPath__c": "1915164a-99ea-a039-0705-2b296dfc277d<8ccbf96a-e729-224a-9085-24bccb8b94b5",
        "%vlocity_namespace%__ProductHierarchyGroupKeyPath__c": "c2ad529d-a871-1bf5-feab-bcea157da521<0663d6a9-d7d2-8696-680e-485a931bf59a",
        "%vlocity_namespace%__ProductHierarchyPath__c": "01t9M000008wrfFQAQ<01tMU000000lEfHYAU",
        "%vlocity_namespace%__ProductId__c": {
            "%vlocity_namespace%__GlobalKey__c": "1915164a-99ea-a039-0705-2b296dfc277d",
            "VlocityDataPackType": "VlocityMatchingKeyObject",
            "VlocityMatchingRecordSourceKey": "Product2/1915164a-99ea-a039-0705-2b296dfc277d",
            "VlocityRecordSObjectType": "Product2"
        },
        "Name": "OverrideDefinition",
        "VlocityDataPackType": "SObject",
        "VlocityRecordSObjectType": "%vlocity_namespace%__OverrideDefinition__c"
    },
    {
        "%vlocity_namespace%__CompiledAttributeOverrideId__c": {
            "VlocityDataPackType": "VlocityMatchingKeyObject",
            "VlocityMatchingRecordSourceKey": "%vlocity_namespace%__CompiledAttributeOverride__c/Generated-625990356",
            "VlocityRecordSObjectType": "%vlocity_namespace%__CompiledAttributeOverride__c"
        },
        "%vlocity_namespace%__IsExclude__c": false,
        "%vlocity_namespace%__OverriddenAttributeAssignmentCategoryId__c": {
            "%vlocity_namespace%__Code__c": "ATTCAT-B2B-HRD-DTL",
            "VlocityDataPackType": "VlocityLookupMatchingKeyObject",
            "VlocityLookupRecordSourceKey": "%vlocity_namespace%__AttributeCategory__c/ATTCAT-B2B-HRD-DTL",
            "VlocityRecordSObjectType": "%vlocity_namespace%__AttributeCategory__c"
        },
        "%vlocity_namespace%__OverriddenAttributeAssignmentId__c": {
            "%vlocity_namespace%__AttributeId__r.%vlocity_namespace%__Code__c": "ATT-ONT-ID",
            "%vlocity_namespace%__IsOverride__c": false,
            "%vlocity_namespace%__ObjectId__c": {
                "%vlocity_namespace%__GlobalKey__c": "8ccbf96a-e729-224a-9085-24bccb8b94b5",
                "VlocityDataPackType": "VlocityLookupMatchingKeyObject",
                "VlocityLookupRecordSourceKey": "Product2/8ccbf96a-e729-224a-9085-24bccb8b94b5",
                "VlocityRecordSObjectType": "Product2"
            },
            "%vlocity_namespace%__OverrideContext__c": null,
            "VlocityDataPackType": "VlocityLookupMatchingKeyObject",
            "VlocityLookupRecordSourceKey": "%vlocity_namespace%__AttributeAssignment__c/f52eeefc-01c1-c398-2159-78b9a9861841",
            "VlocityRecordSObjectType": "%vlocity_namespace%__AttributeAssignment__c"
        },
        "%vlocity_namespace%__OverrideType__c": "Attribute",
        "%vlocity_namespace%__OverridingAttributeAssignmentCategoryId__c": {
            "%vlocity_namespace%__Code__c": "ATTCAT-B2B-HRD-DTL",
            "VlocityDataPackType": "VlocityLookupMatchingKeyObject",
            "VlocityLookupRecordSourceKey": "%vlocity_namespace%__AttributeCategory__c/ATTCAT-B2B-HRD-DTL",
            "VlocityRecordSObjectType": "%vlocity_namespace%__AttributeCategory__c"
        },
        "%vlocity_namespace%__OverridingAttributeAssignmentId__c": {
            "%vlocity_namespace%__AttributeId__r.%vlocity_namespace%__Code__c": "ATT-ONT-ID",
            "%vlocity_namespace%__IsOverride__c": true,
            "%vlocity_namespace%__ObjectId__c": {
                "%vlocity_namespace%__GlobalKey__c": "8ccbf96a-e729-224a-9085-24bccb8b94b5",
                "VlocityDataPackType": "VlocityLookupMatchingKeyObject",
                "VlocityLookupRecordSourceKey": "Product2/8ccbf96a-e729-224a-9085-24bccb8b94b5",
                "VlocityRecordSObjectType": "Product2"
            },
            "%vlocity_namespace%__OverrideContext__c": "2210170403",
            "VlocityDataPackType": "VlocityLookupMatchingKeyObject",
            "VlocityLookupRecordSourceKey": "%vlocity_namespace%__AttributeAssignment__c/fd12b91d-dfb2-2d6c-9262-c1573c186978",
            "VlocityRecordSObjectType": "%vlocity_namespace%__AttributeAssignment__c"
        },
        "%vlocity_namespace%__ProductGroupKey__c": "c2ad529d-a871-1bf5-feab-bcea157da521",
        "%vlocity_namespace%__ProductHierarchyGlobalKeyPath__c": "1915164a-99ea-a039-0705-2b296dfc277d<8ccbf96a-e729-224a-9085-24bccb8b94b5",
        "%vlocity_namespace%__ProductHierarchyGroupKeyPath__c": "c2ad529d-a871-1bf5-feab-bcea157da521<0663d6a9-d7d2-8696-680e-485a931bf59a",
        "%vlocity_namespace%__ProductHierarchyPath__c": "01t9M000008wrfFQAQ<01tMU000000lEfHYAU",
        "%vlocity_namespace%__ProductId__c": {
            "%vlocity_namespace%__GlobalKey__c": "1915164a-99ea-a039-0705-2b296dfc277d",
            "VlocityDataPackType": "VlocityMatchingKeyObject",
            "VlocityMatchingRecordSourceKey": "Product2/1915164a-99ea-a039-0705-2b296dfc277d",
            "VlocityRecordSObjectType": "Product2"
        },
        "Name": "OverrideDefinition",
        "VlocityDataPackType": "SObject",
        "VlocityRecordSObjectType": "%vlocity_namespace%__OverrideDefinition__c"
    },
    {
        "%vlocity_namespace%__CompiledAttributeOverrideId__c": {
            "VlocityDataPackType": "VlocityMatchingKeyObject",
            "VlocityMatchingRecordSourceKey": "%vlocity_namespace%__CompiledAttributeOverride__c/Generated-625990356",
            "VlocityRecordSObjectType": "%vlocity_namespace%__CompiledAttributeOverride__c"
        },
        "%vlocity_namespace%__IsExclude__c": false,
        "%vlocity_namespace%__OverriddenAttributeAssignmentCategoryId__c": {
            "%vlocity_namespace%__Code__c": "ATTCAT-B2B-HRD-DTL",
            "VlocityDataPackType": "VlocityLookupMatchingKeyObject",
            "VlocityLookupRecordSourceKey": "%vlocity_namespace%__AttributeCategory__c/ATTCAT-B2B-HRD-DTL",
            "VlocityRecordSObjectType": "%vlocity_namespace%__AttributeCategory__c"
        },
        "%vlocity_namespace%__OverriddenAttributeAssignmentId__c": {
            "%vlocity_namespace%__AttributeId__r.%vlocity_namespace%__Code__c": "ATT-RTR-TYP",
            "%vlocity_namespace%__IsOverride__c": false,
            "%vlocity_namespace%__ObjectId__c": {
                "%vlocity_namespace%__GlobalKey__c": "8ccbf96a-e729-224a-9085-24bccb8b94b5",
                "VlocityDataPackType": "VlocityLookupMatchingKeyObject",
                "VlocityLookupRecordSourceKey": "Product2/8ccbf96a-e729-224a-9085-24bccb8b94b5",
                "VlocityRecordSObjectType": "Product2"
            },
            "%vlocity_namespace%__OverrideContext__c": null,
            "VlocityDataPackType": "VlocityLookupMatchingKeyObject",
            "VlocityLookupRecordSourceKey": "%vlocity_namespace%__AttributeAssignment__c/b0f35372-3a7a-0bc7-ef46-16c622bec670",
            "VlocityRecordSObjectType": "%vlocity_namespace%__AttributeAssignment__c"
        },
        "%vlocity_namespace%__OverrideType__c": "Attribute",
        "%vlocity_namespace%__OverridingAttributeAssignmentCategoryId__c": {
            "%vlocity_namespace%__Code__c": "ATTCAT-B2B-HRD-DTL",
            "VlocityDataPackType": "VlocityLookupMatchingKeyObject",
            "VlocityLookupRecordSourceKey": "%vlocity_namespace%__AttributeCategory__c/ATTCAT-B2B-HRD-DTL",
            "VlocityRecordSObjectType": "%vlocity_namespace%__AttributeCategory__c"
        },
        "%vlocity_namespace%__OverridingAttributeAssignmentId__c": {
            "%vlocity_namespace%__AttributeId__r.%vlocity_namespace%__Code__c": "ATT-RTR-TYP",
            "%vlocity_namespace%__IsOverride__c": true,
            "%vlocity_namespace%__ObjectId__c": {
                "%vlocity_namespace%__GlobalKey__c": "8ccbf96a-e729-224a-9085-24bccb8b94b5",
                "VlocityDataPackType": "VlocityLookupMatchingKeyObject",
                "VlocityLookupRecordSourceKey": "Product2/8ccbf96a-e729-224a-9085-24bccb8b94b5",
                "VlocityRecordSObjectType": "Product2"
            },
            "%vlocity_namespace%__OverrideContext__c": "2210170403",
            "VlocityDataPackType": "VlocityLookupMatchingKeyObject",
            "VlocityLookupRecordSourceKey": "%vlocity_namespace%__AttributeAssignment__c/16b72288-9b87-a89e-9d38-5033eb38d6de",
            "VlocityRecordSObjectType": "%vlocity_namespace%__AttributeAssignment__c"
        },
        "%vlocity_namespace%__ProductGroupKey__c": "c2ad529d-a871-1bf5-feab-bcea157da521",
        "%vlocity_namespace%__ProductHierarchyGlobalKeyPath__c": "1915164a-99ea-a039-0705-2b296dfc277d<8ccbf96a-e729-224a-9085-24bccb8b94b5",
        "%vlocity_namespace%__ProductHierarchyGroupKeyPath__c": "c2ad529d-a871-1bf5-feab-bcea157da521<0663d6a9-d7d2-8696-680e-485a931bf59a",
        "%vlocity_namespace%__ProductHierarchyPath__c": "01t9M000008wrfFQAQ<01tMU000000lEfHYAU",
        "%vlocity_namespace%__ProductId__c": {
            "%vlocity_namespace%__GlobalKey__c": "1915164a-99ea-a039-0705-2b296dfc277d",
            "VlocityDataPackType": "VlocityMatchingKeyObject",
            "VlocityMatchingRecordSourceKey": "Product2/1915164a-99ea-a039-0705-2b296dfc277d",
            "VlocityRecordSObjectType": "Product2"
        },
        "Name": "OverrideDefinition",
        "VlocityDataPackType": "SObject",
        "VlocityRecordSObjectType": "%vlocity_namespace%__OverrideDefinition__c"
    },
    {
        "%vlocity_namespace%__CompiledAttributeOverrideId__c": {
            "VlocityDataPackType": "VlocityMatchingKeyObject",
            "VlocityMatchingRecordSourceKey": "%vlocity_namespace%__CompiledAttributeOverride__c/Generated1591164009",
            "VlocityRecordSObjectType": "%vlocity_namespace%__CompiledAttributeOverride__c"
        },
        "%vlocity_namespace%__IsExclude__c": false,
        "%vlocity_namespace%__OverriddenAttributeAssignmentCategoryId__c": {
            "%vlocity_namespace%__Code__c": "ATTCAT-B2B-GNR-ATT",
            "VlocityDataPackType": "VlocityLookupMatchingKeyObject",
            "VlocityLookupRecordSourceKey": "%vlocity_namespace%__AttributeCategory__c/ATTCAT-B2B-GNR-ATT",
            "VlocityRecordSObjectType": "%vlocity_namespace%__AttributeCategory__c"
        },
        "%vlocity_namespace%__OverriddenAttributeAssignmentId__c": {
            "%vlocity_namespace%__AttributeId__r.%vlocity_namespace%__Code__c": "ATT-OFF-CODE",
            "%vlocity_namespace%__IsOverride__c": false,
            "%vlocity_namespace%__ObjectId__c": {
                "%vlocity_namespace%__GlobalKey__c": "b664f7e6-2f17-528f-5f1c-0cb5d1943f6e",
                "VlocityDataPackType": "VlocityLookupMatchingKeyObject",
                "VlocityLookupRecordSourceKey": "Product2/b664f7e6-2f17-528f-5f1c-0cb5d1943f6e",
                "VlocityRecordSObjectType": "Product2"
            },
            "%vlocity_namespace%__OverrideContext__c": null,
            "VlocityDataPackType": "VlocityLookupMatchingKeyObject",
            "VlocityLookupRecordSourceKey": "%vlocity_namespace%__AttributeAssignment__c/2924bb85-cbe6-8b03-0b7b-24e58dfb2d3c",
            "VlocityRecordSObjectType": "%vlocity_namespace%__AttributeAssignment__c"
        },
        "%vlocity_namespace%__OverrideType__c": "Attribute",
        "%vlocity_namespace%__OverridingAttributeAssignmentCategoryId__c": {
            "%vlocity_namespace%__Code__c": "ATTCAT-B2B-GNR-ATT",
            "VlocityDataPackType": "VlocityLookupMatchingKeyObject",
            "VlocityLookupRecordSourceKey": "%vlocity_namespace%__AttributeCategory__c/ATTCAT-B2B-GNR-ATT",
            "VlocityRecordSObjectType": "%vlocity_namespace%__AttributeCategory__c"
        },
        "%vlocity_namespace%__OverridingAttributeAssignmentId__c": {
            "%vlocity_namespace%__AttributeId__r.%vlocity_namespace%__Code__c": "ATT-OFF-CODE",
            "%vlocity_namespace%__IsOverride__c": true,
            "%vlocity_namespace%__ObjectId__c": {
                "%vlocity_namespace%__GlobalKey__c": "b664f7e6-2f17-528f-5f1c-0cb5d1943f6e",
                "VlocityDataPackType": "VlocityLookupMatchingKeyObject",
                "VlocityLookupRecordSourceKey": "Product2/b664f7e6-2f17-528f-5f1c-0cb5d1943f6e",
                "VlocityRecordSObjectType": "Product2"
            },
            "%vlocity_namespace%__OverrideContext__c": "878704111",
            "VlocityDataPackType": "VlocityLookupMatchingKeyObject",
            "VlocityLookupRecordSourceKey": "%vlocity_namespace%__AttributeAssignment__c/0918f2eb-1f54-2008-70e9-e069c05c5588",
            "VlocityRecordSObjectType": "%vlocity_namespace%__AttributeAssignment__c"
        },
        "%vlocity_namespace%__ProductGroupKey__c": "c2ad529d-a871-1bf5-feab-bcea157da521",
        "%vlocity_namespace%__ProductHierarchyGlobalKeyPath__c": "1915164a-99ea-a039-0705-2b296dfc277d<b664f7e6-2f17-528f-5f1c-0cb5d1943f6e",
        "%vlocity_namespace%__ProductHierarchyGroupKeyPath__c": "c2ad529d-a871-1bf5-feab-bcea157da521<a628358a-09f5-a511-3723-8a8dd5af3a0a",
        "%vlocity_namespace%__ProductHierarchyPath__c": "01t9M000008wrfFQAQ<01t9M000008duH4QAI",
        "%vlocity_namespace%__ProductId__c": {
            "%vlocity_namespace%__GlobalKey__c": "1915164a-99ea-a039-0705-2b296dfc277d",
            "VlocityDataPackType": "VlocityMatchingKeyObject",
            "VlocityMatchingRecordSourceKey": "Product2/1915164a-99ea-a039-0705-2b296dfc277d",
            "VlocityRecordSObjectType": "Product2"
        },
        "Name": "OverrideDefinition",
        "VlocityDataPackType": "SObject",
        "VlocityRecordSObjectType": "%vlocity_namespace%__OverrideDefinition__c"
    },
    {
        "%vlocity_namespace%__CompiledAttributeOverrideId__c": {
            "VlocityDataPackType": "VlocityMatchingKeyObject",
            "VlocityMatchingRecordSourceKey": "%vlocity_namespace%__CompiledAttributeOverride__c/Generated1591164009",
            "VlocityRecordSObjectType": "%vlocity_namespace%__CompiledAttributeOverride__c"
        },
        "%vlocity_namespace%__IsExclude__c": false,
        "%vlocity_namespace%__OverriddenAttributeAssignmentCategoryId__c": {
            "%vlocity_namespace%__Code__c": "ATTCAT-B2B-IP-DTL",
            "VlocityDataPackType": "VlocityLookupMatchingKeyObject",
            "VlocityLookupRecordSourceKey": "%vlocity_namespace%__AttributeCategory__c/ATTCAT-B2B-IP-DTL",
            "VlocityRecordSObjectType": "%vlocity_namespace%__AttributeCategory__c"
        },
        "%vlocity_namespace%__OverriddenAttributeAssignmentId__c": {
            "%vlocity_namespace%__AttributeId__r.%vlocity_namespace%__Code__c": "ATT-IP-TYP",
            "%vlocity_namespace%__IsOverride__c": false,
            "%vlocity_namespace%__ObjectId__c": {
                "%vlocity_namespace%__GlobalKey__c": "b664f7e6-2f17-528f-5f1c-0cb5d1943f6e",
                "VlocityDataPackType": "VlocityLookupMatchingKeyObject",
                "VlocityLookupRecordSourceKey": "Product2/b664f7e6-2f17-528f-5f1c-0cb5d1943f6e",
                "VlocityRecordSObjectType": "Product2"
            },
            "%vlocity_namespace%__OverrideContext__c": null,
            "VlocityDataPackType": "VlocityLookupMatchingKeyObject",
            "VlocityLookupRecordSourceKey": "%vlocity_namespace%__AttributeAssignment__c/79acef93-e75d-abb3-a253-6d5846c806c6",
            "VlocityRecordSObjectType": "%vlocity_namespace%__AttributeAssignment__c"
        },
        "%vlocity_namespace%__OverrideType__c": "Attribute",
        "%vlocity_namespace%__OverridingAttributeAssignmentCategoryId__c": {
            "%vlocity_namespace%__Code__c": "ATTCAT-B2B-IP-DTL",
            "VlocityDataPackType": "VlocityLookupMatchingKeyObject",
            "VlocityLookupRecordSourceKey": "%vlocity_namespace%__AttributeCategory__c/ATTCAT-B2B-IP-DTL",
            "VlocityRecordSObjectType": "%vlocity_namespace%__AttributeCategory__c"
        },
        "%vlocity_namespace%__OverridingAttributeAssignmentId__c": {
            "%vlocity_namespace%__AttributeId__r.%vlocity_namespace%__Code__c": "ATT-IP-TYP",
            "%vlocity_namespace%__IsOverride__c": true,
            "%vlocity_namespace%__ObjectId__c": {
                "%vlocity_namespace%__GlobalKey__c": "b664f7e6-2f17-528f-5f1c-0cb5d1943f6e",
                "VlocityDataPackType": "VlocityLookupMatchingKeyObject",
                "VlocityLookupRecordSourceKey": "Product2/b664f7e6-2f17-528f-5f1c-0cb5d1943f6e",
                "VlocityRecordSObjectType": "Product2"
            },
            "%vlocity_namespace%__OverrideContext__c": "878704111",
            "VlocityDataPackType": "VlocityLookupMatchingKeyObject",
            "VlocityLookupRecordSourceKey": "%vlocity_namespace%__AttributeAssignment__c/ac0a01aa-e81d-3267-980f-26da3f16b787",
            "VlocityRecordSObjectType": "%vlocity_namespace%__AttributeAssignment__c"
        },
        "%vlocity_namespace%__ProductGroupKey__c": "c2ad529d-a871-1bf5-feab-bcea157da521",
        "%vlocity_namespace%__ProductHierarchyGlobalKeyPath__c": "1915164a-99ea-a039-0705-2b296dfc277d<b664f7e6-2f17-528f-5f1c-0cb5d1943f6e",
        "%vlocity_namespace%__ProductHierarchyGroupKeyPath__c": "c2ad529d-a871-1bf5-feab-bcea157da521<a628358a-09f5-a511-3723-8a8dd5af3a0a",
        "%vlocity_namespace%__ProductHierarchyPath__c": "01t9M000008wrfFQAQ<01t9M000008duH4QAI",
        "%vlocity_namespace%__ProductId__c": {
            "%vlocity_namespace%__GlobalKey__c": "1915164a-99ea-a039-0705-2b296dfc277d",
            "VlocityDataPackType": "VlocityMatchingKeyObject",
            "VlocityMatchingRecordSourceKey": "Product2/1915164a-99ea-a039-0705-2b296dfc277d",
            "VlocityRecordSObjectType": "Product2"
        },
        "Name": "OverrideDefinition",
        "VlocityDataPackType": "SObject",
        "VlocityRecordSObjectType": "%vlocity_namespace%__OverrideDefinition__c"
    },
    {
        "%vlocity_namespace%__CompiledAttributeOverrideId__c": {
            "VlocityDataPackType": "VlocityMatchingKeyObject",
            "VlocityMatchingRecordSourceKey": "%vlocity_namespace%__CompiledAttributeOverride__c/Generated1638520092",
            "VlocityRecordSObjectType": "%vlocity_namespace%__CompiledAttributeOverride__c"
        },
        "%vlocity_namespace%__IsExclude__c": false,
        "%vlocity_namespace%__OverriddenAttributeAssignmentCategoryId__c": {
            "%vlocity_namespace%__Code__c": "ATTCAT-B2B-GNR-ATT",
            "VlocityDataPackType": "VlocityLookupMatchingKeyObject",
            "VlocityLookupRecordSourceKey": "%vlocity_namespace%__AttributeCategory__c/ATTCAT-B2B-GNR-ATT",
            "VlocityRecordSObjectType": "%vlocity_namespace%__AttributeCategory__c"
        },
        "%vlocity_namespace%__OverriddenAttributeAssignmentId__c": {
            "%vlocity_namespace%__AttributeId__r.%vlocity_namespace%__Code__c": "ATT-OFF-CODE",
            "%vlocity_namespace%__IsOverride__c": false,
            "%vlocity_namespace%__ObjectId__c": {
                "%vlocity_namespace%__GlobalKey__c": "c4aeefc0-1ec4-c87b-35e1-fa9938c346fc",
                "VlocityDataPackType": "VlocityLookupMatchingKeyObject",
                "VlocityLookupRecordSourceKey": "Product2/c4aeefc0-1ec4-c87b-35e1-fa9938c346fc",
                "VlocityRecordSObjectType": "Product2"
            },
            "%vlocity_namespace%__OverrideContext__c": null,
            "VlocityDataPackType": "VlocityLookupMatchingKeyObject",
            "VlocityLookupRecordSourceKey": "%vlocity_namespace%__AttributeAssignment__c/27528cf1-9290-ea52-9967-4c86dcd4feb7",
            "VlocityRecordSObjectType": "%vlocity_namespace%__AttributeAssignment__c"
        },
        "%vlocity_namespace%__OverrideType__c": "Attribute",
        "%vlocity_namespace%__OverridingAttributeAssignmentCategoryId__c": {
            "%vlocity_namespace%__Code__c": "ATTCAT-B2B-GNR-ATT",
            "VlocityDataPackType": "VlocityLookupMatchingKeyObject",
            "VlocityLookupRecordSourceKey": "%vlocity_namespace%__AttributeCategory__c/ATTCAT-B2B-GNR-ATT",
            "VlocityRecordSObjectType": "%vlocity_namespace%__AttributeCategory__c"
        },
        "%vlocity_namespace%__OverridingAttributeAssignmentId__c": {
            "%vlocity_namespace%__AttributeId__r.%vlocity_namespace%__Code__c": "ATT-OFF-CODE",
            "%vlocity_namespace%__IsOverride__c": true,
            "%vlocity_namespace%__ObjectId__c": {
                "%vlocity_namespace%__GlobalKey__c": "c4aeefc0-1ec4-c87b-35e1-fa9938c346fc",
                "VlocityDataPackType": "VlocityLookupMatchingKeyObject",
                "VlocityLookupRecordSourceKey": "Product2/c4aeefc0-1ec4-c87b-35e1-fa9938c346fc",
                "VlocityRecordSObjectType": "Product2"
            },
            "%vlocity_namespace%__OverrideContext__c": "1463727310",
            "VlocityDataPackType": "VlocityLookupMatchingKeyObject",
            "VlocityLookupRecordSourceKey": "%vlocity_namespace%__AttributeAssignment__c/153c4b8d-528d-9a7c-f9c7-20538a92e3bf",
            "VlocityRecordSObjectType": "%vlocity_namespace%__AttributeAssignment__c"
        },
        "%vlocity_namespace%__ProductGroupKey__c": "c2ad529d-a871-1bf5-feab-bcea157da521",
        "%vlocity_namespace%__ProductHierarchyGlobalKeyPath__c": "1915164a-99ea-a039-0705-2b296dfc277d<b664f7e6-2f17-528f-5f1c-0cb5d1943f6e<c4aeefc0-1ec4-c87b-35e1-fa9938c346fc",
        "%vlocity_namespace%__ProductHierarchyGroupKeyPath__c": "c2ad529d-a871-1bf5-feab-bcea157da521<a628358a-09f5-a511-3723-8a8dd5af3a0a<794fe000-ecf4-e6a6-0a91-3a23c308c468",
        "%vlocity_namespace%__ProductHierarchyPath__c": "01t9M000008wrfFQAQ<01t9M000008duH4QAI<01t9M000008duIfQAI",
        "%vlocity_namespace%__ProductId__c": {
            "%vlocity_namespace%__GlobalKey__c": "1915164a-99ea-a039-0705-2b296dfc277d",
            "VlocityDataPackType": "VlocityMatchingKeyObject",
            "VlocityMatchingRecordSourceKey": "Product2/1915164a-99ea-a039-0705-2b296dfc277d",
            "VlocityRecordSObjectType": "Product2"
        },
        "Name": "OverrideDefinition",
        "VlocityDataPackType": "SObject",
        "VlocityRecordSObjectType": "%vlocity_namespace%__OverrideDefinition__c"
    },
    {
        "%vlocity_namespace%__CompiledAttributeOverrideId__c": {
            "VlocityDataPackType": "VlocityMatchingKeyObject",
            "VlocityMatchingRecordSourceKey": "%vlocity_namespace%__CompiledAttributeOverride__c/Generated1933369082",
            "VlocityRecordSObjectType": "%vlocity_namespace%__CompiledAttributeOverride__c"
        },
        "%vlocity_namespace%__IsExclude__c": false,
        "%vlocity_namespace%__OverriddenAttributeAssignmentCategoryId__c": {
            "%vlocity_namespace%__Code__c": "ATTCAT-B2B-GNR-ATT",
            "VlocityDataPackType": "VlocityLookupMatchingKeyObject",
            "VlocityLookupRecordSourceKey": "%vlocity_namespace%__AttributeCategory__c/ATTCAT-B2B-GNR-ATT",
            "VlocityRecordSObjectType": "%vlocity_namespace%__AttributeCategory__c"
        },
        "%vlocity_namespace%__OverriddenAttributeAssignmentId__c": {
            "%vlocity_namespace%__AttributeId__r.%vlocity_namespace%__Code__c": "ATT-OFF-CODE",
            "%vlocity_namespace%__IsOverride__c": false,
            "%vlocity_namespace%__ObjectId__c": {
                "%vlocity_namespace%__GlobalKey__c": "38419df5-4332-9cb3-7af4-2c1f07145df4",
                "VlocityDataPackType": "VlocityLookupMatchingKeyObject",
                "VlocityLookupRecordSourceKey": "Product2/38419df5-4332-9cb3-7af4-2c1f07145df4",
                "VlocityRecordSObjectType": "Product2"
            },
            "%vlocity_namespace%__OverrideContext__c": null,
            "VlocityDataPackType": "VlocityLookupMatchingKeyObject",
            "VlocityLookupRecordSourceKey": "%vlocity_namespace%__AttributeAssignment__c/c3b5baaf-a179-7b0e-59de-572fba43f2d7",
            "VlocityRecordSObjectType": "%vlocity_namespace%__AttributeAssignment__c"
        },
        "%vlocity_namespace%__OverrideType__c": "Attribute",
        "%vlocity_namespace%__OverridingAttributeAssignmentCategoryId__c": {
            "%vlocity_namespace%__Code__c": "ATTCAT-B2B-GNR-ATT",
            "VlocityDataPackType": "VlocityLookupMatchingKeyObject",
            "VlocityLookupRecordSourceKey": "%vlocity_namespace%__AttributeCategory__c/ATTCAT-B2B-GNR-ATT",
            "VlocityRecordSObjectType": "%vlocity_namespace%__AttributeCategory__c"
        },
        "%vlocity_namespace%__OverridingAttributeAssignmentId__c": {
            "%vlocity_namespace%__AttributeId__r.%vlocity_namespace%__Code__c": "ATT-OFF-CODE",
            "%vlocity_namespace%__IsOverride__c": true,
            "%vlocity_namespace%__ObjectId__c": {
                "%vlocity_namespace%__GlobalKey__c": "38419df5-4332-9cb3-7af4-2c1f07145df4",
                "VlocityDataPackType": "VlocityLookupMatchingKeyObject",
                "VlocityLookupRecordSourceKey": "Product2/38419df5-4332-9cb3-7af4-2c1f07145df4",
                "VlocityRecordSObjectType": "Product2"
            },
            "%vlocity_namespace%__OverrideContext__c": "1106977395",
            "VlocityDataPackType": "VlocityLookupMatchingKeyObject",
            "VlocityLookupRecordSourceKey": "%vlocity_namespace%__AttributeAssignment__c/141dbe9b-3915-fb7e-8db8-94c402729491",
            "VlocityRecordSObjectType": "%vlocity_namespace%__AttributeAssignment__c"
        },
        "%vlocity_namespace%__ProductGroupKey__c": "c2ad529d-a871-1bf5-feab-bcea157da521",
        "%vlocity_namespace%__ProductHierarchyGlobalKeyPath__c": "1915164a-99ea-a039-0705-2b296dfc277d<38419df5-4332-9cb3-7af4-2c1f07145df4",
        "%vlocity_namespace%__ProductHierarchyGroupKeyPath__c": "c2ad529d-a871-1bf5-feab-bcea157da521<5478a543-058a-6b0a-a273-f39badcacdce",
        "%vlocity_namespace%__ProductHierarchyPath__c": "01t9M000008wrfFQAQ<01t9M000008dnqrQAA",
        "%vlocity_namespace%__ProductId__c": {
            "%vlocity_namespace%__GlobalKey__c": "1915164a-99ea-a039-0705-2b296dfc277d",
            "VlocityDataPackType": "VlocityMatchingKeyObject",
            "VlocityMatchingRecordSourceKey": "Product2/1915164a-99ea-a039-0705-2b296dfc277d",
            "VlocityRecordSObjectType": "Product2"
        },
        "Name": "OverrideDefinition",
        "VlocityDataPackType": "SObject",
        "VlocityRecordSObjectType": "%vlocity_namespace%__OverrideDefinition__c"
    },
    {
        "%vlocity_namespace%__CompiledAttributeOverrideId__c": {
            "VlocityDataPackType": "VlocityMatchingKeyObject",
            "VlocityMatchingRecordSourceKey": "%vlocity_namespace%__CompiledAttributeOverride__c/Generated1933369082",
            "VlocityRecordSObjectType": "%vlocity_namespace%__CompiledAttributeOverride__c"
        },
        "%vlocity_namespace%__IsExclude__c": false,
        "%vlocity_namespace%__OverriddenAttributeAssignmentCategoryId__c": {
            "%vlocity_namespace%__Code__c": "ATTCAT-B2B-INT-DTL",
            "VlocityDataPackType": "VlocityLookupMatchingKeyObject",
            "VlocityLookupRecordSourceKey": "%vlocity_namespace%__AttributeCategory__c/ATTCAT-B2B-INT-DTL",
            "VlocityRecordSObjectType": "%vlocity_namespace%__AttributeCategory__c"
        },
        "%vlocity_namespace%__OverriddenAttributeAssignmentId__c": {
            "%vlocity_namespace%__AttributeId__r.%vlocity_namespace%__Code__c": "ATT-DWN-SPD",
            "%vlocity_namespace%__IsOverride__c": false,
            "%vlocity_namespace%__ObjectId__c": {
                "%vlocity_namespace%__GlobalKey__c": "38419df5-4332-9cb3-7af4-2c1f07145df4",
                "VlocityDataPackType": "VlocityLookupMatchingKeyObject",
                "VlocityLookupRecordSourceKey": "Product2/38419df5-4332-9cb3-7af4-2c1f07145df4",
                "VlocityRecordSObjectType": "Product2"
            },
            "%vlocity_namespace%__OverrideContext__c": null,
            "VlocityDataPackType": "VlocityLookupMatchingKeyObject",
            "VlocityLookupRecordSourceKey": "%vlocity_namespace%__AttributeAssignment__c/135e802e-a9d2-118b-c94a-ea5f0812b2d9",
            "VlocityRecordSObjectType": "%vlocity_namespace%__AttributeAssignment__c"
        },
        "%vlocity_namespace%__OverrideType__c": "Attribute",
        "%vlocity_namespace%__OverridingAttributeAssignmentCategoryId__c": {
            "%vlocity_namespace%__Code__c": "ATTCAT-B2B-INT-DTL",
            "VlocityDataPackType": "VlocityLookupMatchingKeyObject",
            "VlocityLookupRecordSourceKey": "%vlocity_namespace%__AttributeCategory__c/ATTCAT-B2B-INT-DTL",
            "VlocityRecordSObjectType": "%vlocity_namespace%__AttributeCategory__c"
        },
        "%vlocity_namespace%__OverridingAttributeAssignmentId__c": {
            "%vlocity_namespace%__AttributeId__r.%vlocity_namespace%__Code__c": "ATT-DWN-SPD",
            "%vlocity_namespace%__IsOverride__c": true,
            "%vlocity_namespace%__ObjectId__c": {
                "%vlocity_namespace%__GlobalKey__c": "38419df5-4332-9cb3-7af4-2c1f07145df4",
                "VlocityDataPackType": "VlocityLookupMatchingKeyObject",
                "VlocityLookupRecordSourceKey": "Product2/38419df5-4332-9cb3-7af4-2c1f07145df4",
                "VlocityRecordSObjectType": "Product2"
            },
            "%vlocity_namespace%__OverrideContext__c": "1106977395",
            "VlocityDataPackType": "VlocityLookupMatchingKeyObject",
            "VlocityLookupRecordSourceKey": "%vlocity_namespace%__AttributeAssignment__c/60400251-5864-b1d7-fa30-4ffad12f378b",
            "VlocityRecordSObjectType": "%vlocity_namespace%__AttributeAssignment__c"
        },
        "%vlocity_namespace%__ProductGroupKey__c": "c2ad529d-a871-1bf5-feab-bcea157da521",
        "%vlocity_namespace%__ProductHierarchyGlobalKeyPath__c": "1915164a-99ea-a039-0705-2b296dfc277d<38419df5-4332-9cb3-7af4-2c1f07145df4",
        "%vlocity_namespace%__ProductHierarchyGroupKeyPath__c": "c2ad529d-a871-1bf5-feab-bcea157da521<5478a543-058a-6b0a-a273-f39badcacdce",
        "%vlocity_namespace%__ProductHierarchyPath__c": "01t9M000008wrfFQAQ<01t9M000008dnqrQAA",
        "%vlocity_namespace%__ProductId__c": {
            "%vlocity_namespace%__GlobalKey__c": "1915164a-99ea-a039-0705-2b296dfc277d",
            "VlocityDataPackType": "VlocityMatchingKeyObject",
            "VlocityMatchingRecordSourceKey": "Product2/1915164a-99ea-a039-0705-2b296dfc277d",
            "VlocityRecordSObjectType": "Product2"
        },
        "Name": "OverrideDefinition",
        "VlocityDataPackType": "SObject",
        "VlocityRecordSObjectType": "%vlocity_namespace%__OverrideDefinition__c"
    },
    {
        "%vlocity_namespace%__CompiledAttributeOverrideId__c": {
            "VlocityDataPackType": "VlocityMatchingKeyObject",
            "VlocityMatchingRecordSourceKey": "%vlocity_namespace%__CompiledAttributeOverride__c/Generated1933369082",
            "VlocityRecordSObjectType": "%vlocity_namespace%__CompiledAttributeOverride__c"
        },
        "%vlocity_namespace%__IsExclude__c": false,
        "%vlocity_namespace%__OverriddenAttributeAssignmentCategoryId__c": {
            "%vlocity_namespace%__Code__c": "ATTCAT-B2B-INT-DTL",
            "VlocityDataPackType": "VlocityLookupMatchingKeyObject",
            "VlocityLookupRecordSourceKey": "%vlocity_namespace%__AttributeCategory__c/ATTCAT-B2B-INT-DTL",
            "VlocityRecordSObjectType": "%vlocity_namespace%__AttributeCategory__c"
        },
        "%vlocity_namespace%__OverriddenAttributeAssignmentId__c": {
            "%vlocity_namespace%__AttributeId__r.%vlocity_namespace%__Code__c": "ATT-UPL-SPD",
            "%vlocity_namespace%__IsOverride__c": false,
            "%vlocity_namespace%__ObjectId__c": {
                "%vlocity_namespace%__GlobalKey__c": "38419df5-4332-9cb3-7af4-2c1f07145df4",
                "VlocityDataPackType": "VlocityLookupMatchingKeyObject",
                "VlocityLookupRecordSourceKey": "Product2/38419df5-4332-9cb3-7af4-2c1f07145df4",
                "VlocityRecordSObjectType": "Product2"
            },
            "%vlocity_namespace%__OverrideContext__c": null,
            "VlocityDataPackType": "VlocityLookupMatchingKeyObject",
            "VlocityLookupRecordSourceKey": "%vlocity_namespace%__AttributeAssignment__c/fdffeba8-182e-c5f1-f961-1a59953414fb",
            "VlocityRecordSObjectType": "%vlocity_namespace%__AttributeAssignment__c"
        },
        "%vlocity_namespace%__OverrideType__c": "Attribute",
        "%vlocity_namespace%__OverridingAttributeAssignmentCategoryId__c": {
            "%vlocity_namespace%__Code__c": "ATTCAT-B2B-INT-DTL",
            "VlocityDataPackType": "VlocityLookupMatchingKeyObject",
            "VlocityLookupRecordSourceKey": "%vlocity_namespace%__AttributeCategory__c/ATTCAT-B2B-INT-DTL",
            "VlocityRecordSObjectType": "%vlocity_namespace%__AttributeCategory__c"
        },
        "%vlocity_namespace%__OverridingAttributeAssignmentId__c": {
            "%vlocity_namespace%__AttributeId__r.%vlocity_namespace%__Code__c": "ATT-UPL-SPD",
            "%vlocity_namespace%__IsOverride__c": true,
            "%vlocity_namespace%__ObjectId__c": {
                "%vlocity_namespace%__GlobalKey__c": "38419df5-4332-9cb3-7af4-2c1f07145df4",
                "VlocityDataPackType": "VlocityLookupMatchingKeyObject",
                "VlocityLookupRecordSourceKey": "Product2/38419df5-4332-9cb3-7af4-2c1f07145df4",
                "VlocityRecordSObjectType": "Product2"
            },
            "%vlocity_namespace%__OverrideContext__c": "1106977395",
            "VlocityDataPackType": "VlocityLookupMatchingKeyObject",
            "VlocityLookupRecordSourceKey": "%vlocity_namespace%__AttributeAssignment__c/56c27e9e-70db-466f-0449-8225ba4edf5f",
            "VlocityRecordSObjectType": "%vlocity_namespace%__AttributeAssignment__c"
        },
        "%vlocity_namespace%__ProductGroupKey__c": "c2ad529d-a871-1bf5-feab-bcea157da521",
        "%vlocity_namespace%__ProductHierarchyGlobalKeyPath__c": "1915164a-99ea-a039-0705-2b296dfc277d<38419df5-4332-9cb3-7af4-2c1f07145df4",
        "%vlocity_namespace%__ProductHierarchyGroupKeyPath__c": "c2ad529d-a871-1bf5-feab-bcea157da521<5478a543-058a-6b0a-a273-f39badcacdce",
        "%vlocity_namespace%__ProductHierarchyPath__c": "01t9M000008wrfFQAQ<01t9M000008dnqrQAA",
        "%vlocity_namespace%__ProductId__c": {
            "%vlocity_namespace%__GlobalKey__c": "1915164a-99ea-a039-0705-2b296dfc277d",
            "VlocityDataPackType": "VlocityMatchingKeyObject",
            "VlocityMatchingRecordSourceKey": "Product2/1915164a-99ea-a039-0705-2b296dfc277d",
            "VlocityRecordSObjectType": "Product2"
        },
        "Name": "OverrideDefinition",
        "VlocityDataPackType": "SObject",
        "VlocityRecordSObjectType": "%vlocity_namespace%__OverrideDefinition__c"
    },
    {
        "%vlocity_namespace%__IsExclude__c": false,
        "%vlocity_namespace%__OverriddenProductChildItemId__c": {
            "%vlocity_namespace%__GlobalKey__c": "390d3530-982b-4438-d994-1ef40a444a83",
            "VlocityDataPackType": "VlocityLookupMatchingKeyObject",
            "VlocityLookupRecordSourceKey": "%vlocity_namespace%__ProductChildItem__c/390d3530-982b-4438-d994-1ef40a444a83",
            "VlocityRecordSObjectType": "%vlocity_namespace%__ProductChildItem__c"
        },
        "%vlocity_namespace%__OverrideType__c": "Product Definition",
        "%vlocity_namespace%__OverridingProductChildItemId__c": {
            "%vlocity_namespace%__GlobalKey__c": "bcb5aa84-4864-bb73-acf4-ce98cc59afd2",
            "VlocityDataPackType": "VlocityLookupMatchingKeyObject",
            "VlocityLookupRecordSourceKey": "%vlocity_namespace%__ProductChildItem__c/bcb5aa84-4864-bb73-acf4-ce98cc59afd2",
            "VlocityRecordSObjectType": "%vlocity_namespace%__ProductChildItem__c"
        },
        "%vlocity_namespace%__ProductGroupKey__c": "c2ad529d-a871-1bf5-feab-bcea157da521",
        "%vlocity_namespace%__ProductHierarchyGlobalKeyPath__c": "1915164a-99ea-a039-0705-2b296dfc277d<b664f7e6-2f17-528f-5f1c-0cb5d1943f6e<c4aeefc0-1ec4-c87b-35e1-fa9938c346fc",
        "%vlocity_namespace%__ProductHierarchyGroupKeyPath__c": "c2ad529d-a871-1bf5-feab-bcea157da521<a628358a-09f5-a511-3723-8a8dd5af3a0a<794fe000-ecf4-e6a6-0a91-3a23c308c468",
        "%vlocity_namespace%__ProductHierarchyPath__c": "01t9M000008wrfFQAQ<01t9M000008duH4QAI<01t9M000008duIfQAI",
        "%vlocity_namespace%__ProductId__c": {
            "%vlocity_namespace%__GlobalKey__c": "1915164a-99ea-a039-0705-2b296dfc277d",
            "VlocityDataPackType": "VlocityMatchingKeyObject",
            "VlocityMatchingRecordSourceKey": "Product2/1915164a-99ea-a039-0705-2b296dfc277d",
            "VlocityRecordSObjectType": "Product2"
        },
        "Name": "OverrideDefinition",
        "VlocityDataPackType": "SObject",
        "VlocityRecordSObjectType": "%vlocity_namespace%__OverrideDefinition__c"
    }
]